CONTRIBUTING.rst
CONTRIBUTORS.rst
HISTORY.rst
LICENSE
MANIFEST.in
README.rst
pyproject.toml
setup.cfg
setup.py
dmelon/__init__.py
dmelon/dmelon.py
dmelon.egg-info/PKG-INFO
dmelon.egg-info/SOURCES.txt
dmelon.egg-info/dependency_links.txt
dmelon.egg-info/not-zip-safe
dmelon.egg-info/top_level.txt
docs/Makefile
docs/conf.py
docs/contributing.rst
docs/contributors.rst
docs/history.rst
docs/index.rst
docs/installation.rst
docs/make.bat
docs/readme.rst
docs/usage.rst