Metadata-Version: 1.1
Name: dmelon
Version: 0.1.1
Summary: Personal package containing some useful stuff I tend to repeat.
Home-page: https://github.com/DangoMelon/dmelon
Author: Gerardo A. Rivera Tello
Author-email: gerardo_art@me.com
License: MIT license
Keywords: dmelon
Platform: UNKNOWN
Classifier: Development Status :: 2 - Pre-Alpha
Classifier: Intended Audience :: Developers
Classifier: License :: OSI Approved :: MIT License
Classifier: Natural Language :: English
Classifier: Programming Language :: Python :: 3
Classifier: Programming Language :: Python :: 3.6
Classifier: Programming Language :: Python :: 3.7
Classifier: Programming Language :: Python :: 3.8
